Metadata-Version: 2.1
Name: ecoledirecteapi
Version: 0.1
Summary: ecoledirecteapi est une librairie python permetant de communiquer simplement avec l'api ecole directe
Home-page: https://github.com/8borane8/ecoledirecteapi
Author: Borane#9999
License: MIT
Keywords: ecole directe api
Requires-Python: >=3.6
License-File: LICENSE.md
